[{"name":"Глава 2. Управление транспортным средством.","item":[{"amount":"100000","reason":"2.1 ДК","text":"2.1 Управление транспортным средством по полосе встречного движения."},{"amount":"100000","reason":"2.2 ДК","text":"2.2 Езда по железнодорожным путям."},{"amount":"120000","reason":"2.3 ДК","text":"2.3 Управление транспортным средством в состоянии алкогольного или наркотического опьянения."},{"amount":"50000","reason":"2.4 ДК","text":"2.4 Езда в вечернее время [21:00-07:00] без включенных фар."},{"amount":"200000","reason":"2.6 ДК","text":"2.6 Управление транспортным средством без номерных знаков."},{"amount":"100000","reason":"2.7 ДК","text":"2.7 Использование мобильных телефонов за рулем, во время вождения ТС."},{"amount":"150000","reason":"2.8 ДК","text":"2.8 Превышение скоростного режима."}]},{"name":"Глава 3. Положение пешеходов.","item":[{"amount":"200000","reason":"3.1 ДК","text":"3.1 Переход дороги в неположенном месте, либо же за передвижение пешехода по проезжей части дороги."}]},{"name":"Глава 4. Парковка и движение ТС в неположенном месте.","item":[{"amount":"125000","reason":"4.2 ДК","text":"4.2 Движение по тротуарам, велосипедным и пешеходным дорожкам."},{"amount":"125000","reason":"4.3 ДК","text":"4.3 Движение по обочине."}]},{"name":"Глава 5. Затруднение движения.","item":[{"amount":"100000","reason":"5.1 ДК","text":"5.1 Затруднение движения на проезжих частях."},{"amount":"100000","reason":"5.2 ДК","text":"5.2 Затруднение движения на проезжих частях, вследствие чего произошло ДТП."}]}]